{
	"info": {
		"_postman_id": "dcc8d918-a914-41b0-8c47-1e5cd735d825",
		"name": "xAmbit API V0",
		"schema": "https://schema.getpostman.com/json/collection/v2.1.0/collection.json",
		"_exporter_id": "31080727"
	},
	"item": [
		{
			"name": "GST Analysis",
			"item": [
				{
					"name": "Check if GSTIN analysis exists",
					"request": {
						"method": "GET",
						"header": [
							{
								"key": "X-HOST",
								"value": "{{xambit_api_host}}",
								"type": "text"
							},
							{
								"key": "X-KEY",
								"value": "{{xambit_api_key}}",
								"type": "text"
							},
							{
								"key": "Content-Type",
								"value": "application/json",
								"type": "text"
							}
						],
						"url": {
							"raw": "https://xapp-gstr-5qxdkkqowq-el.a.run.app/api/{{xambit_gst_xapp_id}}/gstin/{{gstin_number}}/exists",
							"protocol": "https",
							"host": [
								"xapp-gstr-5qxdkkqowq-el",
								"a",
								"run",
								"app"
							],
							"path": [
								"api",
								"{{xambit_gst_xapp_id}}",
								"gstin",
								"{{gstin_number}}",
								"exists"
							]
						},
						"description": "This requests checks if you have already initiated analysis request for the same GSTIN. It is a good idea to check this before initiating a fresh new request.\n\nIt will return 200 OK if GSTIN already exists in the system. You can then get on with rest of workflow like OTP auth flow, requesting analysis etc.\n\nIf GSTIN does not exist, it will return a 404. Isn't that cool? Well maybe not!"
					},
					"response": [
						{
							"name": "Check if GSTIN analysis exists",
							"originalRequest": {
								"method": "GET",
								"header": [
									{
										"key": "X-HOST",
										"value": "{{xambit_api_host}}",
										"type": "text"
									},
									{
										"key": "X-KEY",
										"value": "{{xambit_api_key}}",
										"type": "text"
									},
									{
										"key": "Content-Type",
										"value": "application/json",
										"type": "text"
									}
								],
								"url": {
									"raw": "https://xapp-gstr-5qxdkkqowq-el.a.run.app/api/{{xambit_gst_xapp_id}}/gstin/{{gstin_number}}",
									"protocol": "https",
									"host": [
										"xapp-gstr-5qxdkkqowq-el",
										"a",
										"run",
										"app"
									],
									"path": [
										"api",
										"{{xambit_gst_xapp_id}}",
										"gstin",
										"{{gstin_number}}"
									]
								}
							},
							"status": "OK",
							"code": 200,
							"_postman_previewlanguage": "json",
							"header": [
								{
									"key": "content-type",
									"value": "application/json"
								},
								{
									"key": "Content-Length",
									"value": "1091"
								},
								{
									"key": "date",
									"value": "Fri, 17 Nov 2023 06:06:36 GMT"
								},
								{
									"key": "server",
									"value": "Google Frontend"
								},
								{
									"key": "traceparent",
									"value": "00-1678074014e92c6436b0fb04e2d91371-ca8df44bfb88b0ae-01"
								},
								{
									"key": "x-cloud-trace-context",
									"value": "1678074014e92c6436b0fb04e2d91371/14595590574557409454;o=1"
								},
								{
									"key": "Alt-Svc",
									"value": "h3=\":443\"; ma=2592000,h3-29=\":443\"; ma=2592000"
								}
							],
							"cookie": [],
							"body": "{\n    \"id\": \"g-col-01HF64AXQD9HRDETCAA1SH4SN9\",\n    \"gstin\": \"29AAPCM6632E1Z5\",\n    \"status\": 0,\n    \"business\": {\n        \"name\": \"MYTHIKSHA SCHOOL PRIVATE LIMITED\",\n        \"ids\": [\n            {\n                \"id_kind\": 1,\n                \"id\": \"29AAPCM6632E1Z5\"\n            },\n            {\n                \"id_kind\": 2,\n                \"id\": \"AAPCM6632E\"\n            }\n        ],\n        \"promoters\": [],\n        \"trade_name\": null,\n        \"alt_name\": null,\n        \"address\": {\n            \"line1\": \"L-148, HSR LAYOUT\",\n            \"line2\": \"5th Main Road\",\n            \"city\": \"Bengaluru\",\n            \"state_code\": null,\n            \"state\": \"Karnataka\",\n            \"postal_code\": \"560102\",\n            \"country\": \"IN\"\n        },\n        \"other_ids\": [],\n        \"email\": null,\n        \"phone\": null,\n        \"bank\": null,\n        \"cheque\": null,\n        \"wire\": null,\n        \"website\": null\n    },\n    \"gstrbusiness\": {\n        \"kind\": \"Private Limited Company\",\n        \"jurisdiction_name\": \"RANGE-CSD5\",\n        \"jurisdiction_code\": \"YV0503\",\n        \"taxpayer_kind\": \"Regular\",\n        \"einvoice_status\": false,\n        \"nature_of_business\": [\n            \"Supplier of Services\"\n        ],\n        \"date_of_registration\": \"2022-07-07\",\n        \"jurisdiction_state_name\": \"LGSTO 17- Bengaluru\",\n        \"jurisdiction_state_code\": \"KA130\",\n        \"date_cancel\": null\n    },\n    \"entries\": [],\n    \"metrics\": [],\n    \"created\": \"2023-11-14 05:19:46.546542\",\n    \"updated\": \"2023-11-14 05:19:46.546542\",\n    \"period\": null,\n    \"authdate\": null,\n    \"creator\": {\n        \"id\": \"u-01H7CDJW728ZCAA0C7XYNNXFVT\",\n        \"name\": \"Chahat\",\n        \"email\": \"chahat@xambit.io\",\n        \"perm\": 2\n    }\n}"
						}
					]
				},
				{
					"name": "Create new GSTIN for analysis",
					"request": {
						"method": "POST",
						"header": [
							{
								"key": "X-HOST",
								"value": "{{xambit_api_host}}",
								"type": "text"
							},
							{
								"key": "X-KEY",
								"value": "{{xambit_api_key}}",
								"type": "text"
							},
							{
								"key": "Content-Type",
								"value": "application/json",
								"type": "text"
							}
						],
						"url": {
							"raw": "https://xapp-gstr-5qxdkkqowq-el.a.run.app/api/{{xambit_gst_xapp_id}}/gstin/{{gstin_number}}",
							"protocol": "https",
							"host": [
								"xapp-gstr-5qxdkkqowq-el",
								"a",
								"run",
								"app"
							],
							"path": [
								"api",
								"{{xambit_gst_xapp_id}}",
								"gstin",
								"{{gstin_number}}"
							]
						},
						"description": "This requests creates a new GSTIN for analysis in the system. Creating a new GSTIN does not actually kick-off the analysis. You will have to initiate analysis separately after auth flow.\n\nNote that this step does not need OTP or other credentials for the GST portal. Those parameters are part of a separate API flow (OTP validation). Make sure you are putting GSTIN of the parties you know (like your customers) who have consented to doing this."
					},
					"response": [
						{
							"name": "Check if GSTIN analysis exists",
							"originalRequest": {
								"method": "GET",
								"header": [
									{
										"key": "X-HOST",
										"value": "{{xambit_api_host}}",
										"type": "text"
									},
									{
										"key": "X-KEY",
										"value": "{{xambit_api_key}}",
										"type": "text"
									},
									{
										"key": "Content-Type",
										"value": "application/json",
										"type": "text"
									}
								],
								"url": {
									"raw": "https://xapp-gstr-5qxdkkqowq-el.a.run.app/api/{{xambit_gst_xapp_id}}/gstin/{{gstin_number}}",
									"protocol": "https",
									"host": [
										"xapp-gstr-5qxdkkqowq-el",
										"a",
										"run",
										"app"
									],
									"path": [
										"api",
										"{{xambit_gst_xapp_id}}",
										"gstin",
										"{{gstin_number}}"
									]
								}
							},
							"status": "OK",
							"code": 200,
							"_postman_previewlanguage": "json",
							"header": [
								{
									"key": "content-type",
									"value": "application/json"
								},
								{
									"key": "Content-Length",
									"value": "1091"
								},
								{
									"key": "date",
									"value": "Fri, 17 Nov 2023 06:06:36 GMT"
								},
								{
									"key": "server",
									"value": "Google Frontend"
								},
								{
									"key": "traceparent",
									"value": "00-1678074014e92c6436b0fb04e2d91371-ca8df44bfb88b0ae-01"
								},
								{
									"key": "x-cloud-trace-context",
									"value": "1678074014e92c6436b0fb04e2d91371/14595590574557409454;o=1"
								},
								{
									"key": "Alt-Svc",
									"value": "h3=\":443\"; ma=2592000,h3-29=\":443\"; ma=2592000"
								}
							],
							"cookie": [],
							"body": "{\n    \"id\": \"g-col-01HF64AXQD9HRDETCAA1SH4SN9\",\n    \"gstin\": \"29AAPCM6632E1Z5\",\n    \"status\": 0,\n    \"business\": {\n        \"name\": \"MYTHIKSHA SCHOOL PRIVATE LIMITED\",\n        \"ids\": [\n            {\n                \"id_kind\": 1,\n                \"id\": \"29AAPCM6632E1Z5\"\n            },\n            {\n                \"id_kind\": 2,\n                \"id\": \"AAPCM6632E\"\n            }\n        ],\n        \"promoters\": [],\n        \"trade_name\": null,\n        \"alt_name\": null,\n        \"address\": {\n            \"line1\": \"L-148, HSR LAYOUT\",\n            \"line2\": \"5th Main Road\",\n            \"city\": \"Bengaluru\",\n            \"state_code\": null,\n            \"state\": \"Karnataka\",\n            \"postal_code\": \"560102\",\n            \"country\": \"IN\"\n        },\n        \"other_ids\": [],\n        \"email\": null,\n        \"phone\": null,\n        \"bank\": null,\n        \"cheque\": null,\n        \"wire\": null,\n        \"website\": null\n    },\n    \"gstrbusiness\": {\n        \"kind\": \"Private Limited Company\",\n        \"jurisdiction_name\": \"RANGE-CSD5\",\n        \"jurisdiction_code\": \"YV0503\",\n        \"taxpayer_kind\": \"Regular\",\n        \"einvoice_status\": false,\n        \"nature_of_business\": [\n            \"Supplier of Services\"\n        ],\n        \"date_of_registration\": \"2022-07-07\",\n        \"jurisdiction_state_name\": \"LGSTO 17- Bengaluru\",\n        \"jurisdiction_state_code\": \"KA130\",\n        \"date_cancel\": null\n    },\n    \"entries\": [],\n    \"metrics\": [],\n    \"created\": \"2023-11-14 05:19:46.546542\",\n    \"updated\": \"2023-11-14 05:19:46.546542\",\n    \"period\": null,\n    \"authdate\": null,\n    \"creator\": {\n        \"id\": \"u-01H7CDJW728ZCAA0C7XYNNXFVT\",\n        \"name\": \"Chahat\",\n        \"email\": \"chahat@xambit.io\",\n        \"perm\": 2\n    }\n}"
						}
					]
				},
				{
					"name": "Delete existing GSTIN and Analysis",
					"request": {
						"method": "DELETE",
						"header": [
							{
								"key": "X-HOST",
								"value": "{{xambit_api_host}}",
								"type": "text"
							},
							{
								"key": "X-KEY",
								"value": "{{xambit_api_key}}",
								"type": "text"
							},
							{
								"key": "Content-Type",
								"value": "application/json",
								"type": "text"
							}
						],
						"url": {
							"raw": "https://xapp-gstr-5qxdkkqowq-el.a.run.app/api/{{xambit_gst_xapp_id}}/gstin/{{gstin_number}}",
							"protocol": "https",
							"host": [
								"xapp-gstr-5qxdkkqowq-el",
								"a",
								"run",
								"app"
							],
							"path": [
								"api",
								"{{xambit_gst_xapp_id}}",
								"gstin",
								"{{gstin_number}}"
							]
						},
						"description": "This requests creates a deletes a GSTIN and all the related analysis for that GSTIN from xambit system. Be careful! All data and analysis for that GSTIN will be lost and not recoverable. However, you can re-trigger the analysis request for that GSTIN using other API endpoints. Remember that those API requests cost $$ 😊, so don't delete analysis unless you know why!"
					},
					"response": [
						{
							"name": "Check if GSTIN analysis exists",
							"originalRequest": {
								"method": "GET",
								"header": [
									{
										"key": "X-HOST",
										"value": "{{xambit_api_host}}",
										"type": "text"
									},
									{
										"key": "X-KEY",
										"value": "{{xambit_api_key}}",
										"type": "text"
									},
									{
										"key": "Content-Type",
										"value": "application/json",
										"type": "text"
									}
								],
								"url": {
									"raw": "https://xapp-gstr-5qxdkkqowq-el.a.run.app/api/{{xambit_gst_xapp_id}}/gstin/{{gstin_number}}",
									"protocol": "https",
									"host": [
										"xapp-gstr-5qxdkkqowq-el",
										"a",
										"run",
										"app"
									],
									"path": [
										"api",
										"{{xambit_gst_xapp_id}}",
										"gstin",
										"{{gstin_number}}"
									]
								}
							},
							"status": "OK",
							"code": 200,
							"_postman_previewlanguage": "json",
							"header": [
								{
									"key": "content-type",
									"value": "application/json"
								},
								{
									"key": "Content-Length",
									"value": "1091"
								},
								{
									"key": "date",
									"value": "Fri, 17 Nov 2023 06:06:36 GMT"
								},
								{
									"key": "server",
									"value": "Google Frontend"
								},
								{
									"key": "traceparent",
									"value": "00-1678074014e92c6436b0fb04e2d91371-ca8df44bfb88b0ae-01"
								},
								{
									"key": "x-cloud-trace-context",
									"value": "1678074014e92c6436b0fb04e2d91371/14595590574557409454;o=1"
								},
								{
									"key": "Alt-Svc",
									"value": "h3=\":443\"; ma=2592000,h3-29=\":443\"; ma=2592000"
								}
							],
							"cookie": [],
							"body": "{\n    \"id\": \"g-col-01HF64AXQD9HRDETCAA1SH4SN9\",\n    \"gstin\": \"29AAPCM6632E1Z5\",\n    \"status\": 0,\n    \"business\": {\n        \"name\": \"MYTHIKSHA SCHOOL PRIVATE LIMITED\",\n        \"ids\": [\n            {\n                \"id_kind\": 1,\n                \"id\": \"29AAPCM6632E1Z5\"\n            },\n            {\n                \"id_kind\": 2,\n                \"id\": \"AAPCM6632E\"\n            }\n        ],\n        \"promoters\": [],\n        \"trade_name\": null,\n        \"alt_name\": null,\n        \"address\": {\n            \"line1\": \"L-148, HSR LAYOUT\",\n            \"line2\": \"5th Main Road\",\n            \"city\": \"Bengaluru\",\n            \"state_code\": null,\n            \"state\": \"Karnataka\",\n            \"postal_code\": \"560102\",\n            \"country\": \"IN\"\n        },\n        \"other_ids\": [],\n        \"email\": null,\n        \"phone\": null,\n        \"bank\": null,\n        \"cheque\": null,\n        \"wire\": null,\n        \"website\": null\n    },\n    \"gstrbusiness\": {\n        \"kind\": \"Private Limited Company\",\n        \"jurisdiction_name\": \"RANGE-CSD5\",\n        \"jurisdiction_code\": \"YV0503\",\n        \"taxpayer_kind\": \"Regular\",\n        \"einvoice_status\": false,\n        \"nature_of_business\": [\n            \"Supplier of Services\"\n        ],\n        \"date_of_registration\": \"2022-07-07\",\n        \"jurisdiction_state_name\": \"LGSTO 17- Bengaluru\",\n        \"jurisdiction_state_code\": \"KA130\",\n        \"date_cancel\": null\n    },\n    \"entries\": [],\n    \"metrics\": [],\n    \"created\": \"2023-11-14 05:19:46.546542\",\n    \"updated\": \"2023-11-14 05:19:46.546542\",\n    \"period\": null,\n    \"authdate\": null,\n    \"creator\": {\n        \"id\": \"u-01H7CDJW728ZCAA0C7XYNNXFVT\",\n        \"name\": \"Chahat\",\n        \"email\": \"chahat@xambit.io\",\n        \"perm\": 2\n    }\n}"
						}
					]
				},
				{
					"name": "Get data for this GSTIN",
					"request": {
						"method": "GET",
						"header": [
							{
								"key": "X-HOST",
								"value": "{{xambit_api_host}}",
								"type": "text"
							},
							{
								"key": "X-KEY",
								"value": "{{xambit_api_key}}",
								"type": "text"
							},
							{
								"key": "Content-Type",
								"value": "application/json",
								"type": "text"
							}
						],
						"url": {
							"raw": "https://xapp-gstr-5qxdkkqowq-el.a.run.app/api/{{xambit_gst_xapp_id}}/gstin/{{gstin_number}}",
							"protocol": "https",
							"host": [
								"xapp-gstr-5qxdkkqowq-el",
								"a",
								"run",
								"app"
							],
							"path": [
								"api",
								"{{xambit_gst_xapp_id}}",
								"gstin",
								"{{gstin_number}}"
							]
						},
						"description": "This requests creates a new GSTIN for analysis in the system. Note that this step does not need OTP or other credentials for the GST portal. Those parameters are part of a separate API flow (OTP validation)"
					},
					"response": [
						{
							"name": "Check if GSTIN analysis exists",
							"originalRequest": {
								"method": "GET",
								"header": [
									{
										"key": "X-HOST",
										"value": "{{xambit_api_host}}",
										"type": "text"
									},
									{
										"key": "X-KEY",
										"value": "{{xambit_api_key}}",
										"type": "text"
									},
									{
										"key": "Content-Type",
										"value": "application/json",
										"type": "text"
									}
								],
								"url": {
									"raw": "https://xapp-gstr-5qxdkkqowq-el.a.run.app/api/{{xambit_gst_xapp_id}}/gstin/{{gstin_number}}",
									"protocol": "https",
									"host": [
										"xapp-gstr-5qxdkkqowq-el",
										"a",
										"run",
										"app"
									],
									"path": [
										"api",
										"{{xambit_gst_xapp_id}}",
										"gstin",
										"{{gstin_number}}"
									]
								}
							},
							"status": "OK",
							"code": 200,
							"_postman_previewlanguage": "json",
							"header": [
								{
									"key": "content-type",
									"value": "application/json"
								},
								{
									"key": "Content-Length",
									"value": "1091"
								},
								{
									"key": "date",
									"value": "Fri, 17 Nov 2023 06:06:36 GMT"
								},
								{
									"key": "server",
									"value": "Google Frontend"
								},
								{
									"key": "traceparent",
									"value": "00-1678074014e92c6436b0fb04e2d91371-ca8df44bfb88b0ae-01"
								},
								{
									"key": "x-cloud-trace-context",
									"value": "1678074014e92c6436b0fb04e2d91371/14595590574557409454;o=1"
								},
								{
									"key": "Alt-Svc",
									"value": "h3=\":443\"; ma=2592000,h3-29=\":443\"; ma=2592000"
								}
							],
							"cookie": [],
							"body": "{\n    \"id\": \"g-col-01HF64AXQD9HRDETCAA1SH4SN9\",\n    \"gstin\": \"29AAPCM6632E1Z5\",\n    \"status\": 0,\n    \"business\": {\n        \"name\": \"MYTHIKSHA SCHOOL PRIVATE LIMITED\",\n        \"ids\": [\n            {\n                \"id_kind\": 1,\n                \"id\": \"29AAPCM6632E1Z5\"\n            },\n            {\n                \"id_kind\": 2,\n                \"id\": \"AAPCM6632E\"\n            }\n        ],\n        \"promoters\": [],\n        \"trade_name\": null,\n        \"alt_name\": null,\n        \"address\": {\n            \"line1\": \"L-148, HSR LAYOUT\",\n            \"line2\": \"5th Main Road\",\n            \"city\": \"Bengaluru\",\n            \"state_code\": null,\n            \"state\": \"Karnataka\",\n            \"postal_code\": \"560102\",\n            \"country\": \"IN\"\n        },\n        \"other_ids\": [],\n        \"email\": null,\n        \"phone\": null,\n        \"bank\": null,\n        \"cheque\": null,\n        \"wire\": null,\n        \"website\": null\n    },\n    \"gstrbusiness\": {\n        \"kind\": \"Private Limited Company\",\n        \"jurisdiction_name\": \"RANGE-CSD5\",\n        \"jurisdiction_code\": \"YV0503\",\n        \"taxpayer_kind\": \"Regular\",\n        \"einvoice_status\": false,\n        \"nature_of_business\": [\n            \"Supplier of Services\"\n        ],\n        \"date_of_registration\": \"2022-07-07\",\n        \"jurisdiction_state_name\": \"LGSTO 17- Bengaluru\",\n        \"jurisdiction_state_code\": \"KA130\",\n        \"date_cancel\": null\n    },\n    \"entries\": [],\n    \"metrics\": [],\n    \"created\": \"2023-11-14 05:19:46.546542\",\n    \"updated\": \"2023-11-14 05:19:46.546542\",\n    \"period\": null,\n    \"authdate\": null,\n    \"creator\": {\n        \"id\": \"u-01H7CDJW728ZCAA0C7XYNNXFVT\",\n        \"name\": \"Chahat\",\n        \"email\": \"chahat@xambit.io\",\n        \"perm\": 2\n    }\n}"
						}
					]
				},
				{
					"name": "Start OTP Auth Flow for a GSTIN",
					"protocolProfileBehavior": {
						"disabledSystemHeaders": {
							"content-type": true
						}
					},
					"request": {
						"method": "POST",
						"header": [
							{
								"key": "X-HOST",
								"value": "{{xambit_api_host}}",
								"type": "text"
							},
							{
								"key": "X-KEY",
								"value": "{{xambit_api_key}}",
								"type": "text"
							},
							{
								"key": "Content-Type",
								"value": "application/json",
								"type": "text"
							}
						],
						"body": {
							"mode": "raw",
							"raw": "{\n    \"gst_portal_user_name\": \"{{gstin_username}}\",\n    \"otp\": null\n}"
						},
						"url": {
							"raw": "https://xapp-gstr-5qxdkkqowq-el.a.run.app/api/{{xambit_gst_xapp_id}}/gstin/{{gstin_number}}/otp",
							"protocol": "https",
							"host": [
								"xapp-gstr-5qxdkkqowq-el",
								"a",
								"run",
								"app"
							],
							"path": [
								"api",
								"{{xambit_gst_xapp_id}}",
								"gstin",
								"{{gstin_number}}",
								"otp"
							]
						},
						"description": "This requests starts the OTP based auth flow for a particular GSTIN. Make sure that you have already created the GSTIN in the system using POST API documented earlier. The workflow is: you'd request OTP by first calling this endpoint and then share the OTP with xAmbit's machines by making call to {{this endpoint}}/valid endpoint once OTP is received (documented next in this collection).  \n  \nMake sure you've are initiating this on behalf of your customer who has consented for this. You'll need to know their GSTIN portal user name. They'll receive an OTP on official mobile number for consent.  \n  \nDon't do this on using random GSTINs from public information etc."
					},
					"response": [
						{
							"name": "Check if GSTIN analysis exists",
							"originalRequest": {
								"method": "GET",
								"header": [
									{
										"key": "X-HOST",
										"value": "{{xambit_api_host}}",
										"type": "text"
									},
									{
										"key": "X-KEY",
										"value": "{{xambit_api_key}}",
										"type": "text"
									},
									{
										"key": "Content-Type",
										"value": "application/json",
										"type": "text"
									}
								],
								"url": {
									"raw": "https://xapp-gstr-5qxdkkqowq-el.a.run.app/api/{{xambit_gst_xapp_id}}/gstin/{{gstin_number}}",
									"protocol": "https",
									"host": [
										"xapp-gstr-5qxdkkqowq-el",
										"a",
										"run",
										"app"
									],
									"path": [
										"api",
										"{{xambit_gst_xapp_id}}",
										"gstin",
										"{{gstin_number}}"
									]
								}
							},
							"status": "OK",
							"code": 200,
							"_postman_previewlanguage": "json",
							"header": [
								{
									"key": "content-type",
									"value": "application/json"
								},
								{
									"key": "Content-Length",
									"value": "1091"
								},
								{
									"key": "date",
									"value": "Fri, 17 Nov 2023 06:06:36 GMT"
								},
								{
									"key": "server",
									"value": "Google Frontend"
								},
								{
									"key": "traceparent",
									"value": "00-1678074014e92c6436b0fb04e2d91371-ca8df44bfb88b0ae-01"
								},
								{
									"key": "x-cloud-trace-context",
									"value": "1678074014e92c6436b0fb04e2d91371/14595590574557409454;o=1"
								},
								{
									"key": "Alt-Svc",
									"value": "h3=\":443\"; ma=2592000,h3-29=\":443\"; ma=2592000"
								}
							],
							"cookie": [],
							"body": "{\n    \"id\": \"g-col-01HF64AXQD9HRDETCAA1SH4SN9\",\n    \"gstin\": \"29AAPCM6632E1Z5\",\n    \"status\": 0,\n    \"business\": {\n        \"name\": \"MYTHIKSHA SCHOOL PRIVATE LIMITED\",\n        \"ids\": [\n            {\n                \"id_kind\": 1,\n                \"id\": \"29AAPCM6632E1Z5\"\n            },\n            {\n                \"id_kind\": 2,\n                \"id\": \"AAPCM6632E\"\n            }\n        ],\n        \"promoters\": [],\n        \"trade_name\": null,\n        \"alt_name\": null,\n        \"address\": {\n            \"line1\": \"L-148, HSR LAYOUT\",\n            \"line2\": \"5th Main Road\",\n            \"city\": \"Bengaluru\",\n            \"state_code\": null,\n            \"state\": \"Karnataka\",\n            \"postal_code\": \"560102\",\n            \"country\": \"IN\"\n        },\n        \"other_ids\": [],\n        \"email\": null,\n        \"phone\": null,\n        \"bank\": null,\n        \"cheque\": null,\n        \"wire\": null,\n        \"website\": null\n    },\n    \"gstrbusiness\": {\n        \"kind\": \"Private Limited Company\",\n        \"jurisdiction_name\": \"RANGE-CSD5\",\n        \"jurisdiction_code\": \"YV0503\",\n        \"taxpayer_kind\": \"Regular\",\n        \"einvoice_status\": false,\n        \"nature_of_business\": [\n            \"Supplier of Services\"\n        ],\n        \"date_of_registration\": \"2022-07-07\",\n        \"jurisdiction_state_name\": \"LGSTO 17- Bengaluru\",\n        \"jurisdiction_state_code\": \"KA130\",\n        \"date_cancel\": null\n    },\n    \"entries\": [],\n    \"metrics\": [],\n    \"created\": \"2023-11-14 05:19:46.546542\",\n    \"updated\": \"2023-11-14 05:19:46.546542\",\n    \"period\": null,\n    \"authdate\": null,\n    \"creator\": {\n        \"id\": \"u-01H7CDJW728ZCAA0C7XYNNXFVT\",\n        \"name\": \"Chahat\",\n        \"email\": \"chahat@xambit.io\",\n        \"perm\": 2\n    }\n}"
						}
					]
				},
				{
					"name": "Validate OTP for already initiated Auth Flow for a GSTIN",
					"request": {
						"method": "POST",
						"header": [
							{
								"key": "X-HOST",
								"value": "{{xambit_api_host}}",
								"type": "text"
							},
							{
								"key": "X-KEY",
								"value": "{{xambit_api_key}}",
								"type": "text"
							},
							{
								"key": "Content-Type",
								"value": "application/json",
								"type": "text"
							}
						],
						"body": {
							"mode": "raw",
							"raw": "{\n    \"gst_portal_user_name\": \"{{gstin_username}}\",\n    \"otp\": \"<string of OTP>\"\n}"
						},
						"url": {
							"raw": "https://xapp-gstr-5qxdkkqowq-el.a.run.app/api/{{xambit_gst_xapp_id}}/gstin/{{gstin_number}}/otp/valid",
							"protocol": "https",
							"host": [
								"xapp-gstr-5qxdkkqowq-el",
								"a",
								"run",
								"app"
							],
							"path": [
								"api",
								"{{xambit_gst_xapp_id}}",
								"gstin",
								"{{gstin_number}}",
								"otp",
								"valid"
							]
						},
						"description": "This requests starts the validates the OTP received from GSTIN portal by sending it to xAmbit's system. This endpoint should be called only after starting the OTP auth flow using \\`start OTP \\` part documented earlier."
					},
					"response": [
						{
							"name": "Check if GSTIN analysis exists",
							"originalRequest": {
								"method": "GET",
								"header": [
									{
										"key": "X-HOST",
										"value": "{{xambit_api_host}}",
										"type": "text"
									},
									{
										"key": "X-KEY",
										"value": "{{xambit_api_key}}",
										"type": "text"
									},
									{
										"key": "Content-Type",
										"value": "application/json",
										"type": "text"
									}
								],
								"url": {
									"raw": "https://xapp-gstr-5qxdkkqowq-el.a.run.app/api/{{xambit_gst_xapp_id}}/gstin/{{gstin_number}}",
									"protocol": "https",
									"host": [
										"xapp-gstr-5qxdkkqowq-el",
										"a",
										"run",
										"app"
									],
									"path": [
										"api",
										"{{xambit_gst_xapp_id}}",
										"gstin",
										"{{gstin_number}}"
									]
								}
							},
							"status": "OK",
							"code": 200,
							"_postman_previewlanguage": "json",
							"header": [
								{
									"key": "content-type",
									"value": "application/json"
								},
								{
									"key": "Content-Length",
									"value": "1091"
								},
								{
									"key": "date",
									"value": "Fri, 17 Nov 2023 06:06:36 GMT"
								},
								{
									"key": "server",
									"value": "Google Frontend"
								},
								{
									"key": "traceparent",
									"value": "00-1678074014e92c6436b0fb04e2d91371-ca8df44bfb88b0ae-01"
								},
								{
									"key": "x-cloud-trace-context",
									"value": "1678074014e92c6436b0fb04e2d91371/14595590574557409454;o=1"
								},
								{
									"key": "Alt-Svc",
									"value": "h3=\":443\"; ma=2592000,h3-29=\":443\"; ma=2592000"
								}
							],
							"cookie": [],
							"body": "{\n    \"id\": \"g-col-01HF64AXQD9HRDETCAA1SH4SN9\",\n    \"gstin\": \"29AAPCM6632E1Z5\",\n    \"status\": 0,\n    \"business\": {\n        \"name\": \"MYTHIKSHA SCHOOL PRIVATE LIMITED\",\n        \"ids\": [\n            {\n                \"id_kind\": 1,\n                \"id\": \"29AAPCM6632E1Z5\"\n            },\n            {\n                \"id_kind\": 2,\n                \"id\": \"AAPCM6632E\"\n            }\n        ],\n        \"promoters\": [],\n        \"trade_name\": null,\n        \"alt_name\": null,\n        \"address\": {\n            \"line1\": \"L-148, HSR LAYOUT\",\n            \"line2\": \"5th Main Road\",\n            \"city\": \"Bengaluru\",\n            \"state_code\": null,\n            \"state\": \"Karnataka\",\n            \"postal_code\": \"560102\",\n            \"country\": \"IN\"\n        },\n        \"other_ids\": [],\n        \"email\": null,\n        \"phone\": null,\n        \"bank\": null,\n        \"cheque\": null,\n        \"wire\": null,\n        \"website\": null\n    },\n    \"gstrbusiness\": {\n        \"kind\": \"Private Limited Company\",\n        \"jurisdiction_name\": \"RANGE-CSD5\",\n        \"jurisdiction_code\": \"YV0503\",\n        \"taxpayer_kind\": \"Regular\",\n        \"einvoice_status\": false,\n        \"nature_of_business\": [\n            \"Supplier of Services\"\n        ],\n        \"date_of_registration\": \"2022-07-07\",\n        \"jurisdiction_state_name\": \"LGSTO 17- Bengaluru\",\n        \"jurisdiction_state_code\": \"KA130\",\n        \"date_cancel\": null\n    },\n    \"entries\": [],\n    \"metrics\": [],\n    \"created\": \"2023-11-14 05:19:46.546542\",\n    \"updated\": \"2023-11-14 05:19:46.546542\",\n    \"period\": null,\n    \"authdate\": null,\n    \"creator\": {\n        \"id\": \"u-01H7CDJW728ZCAA0C7XYNNXFVT\",\n        \"name\": \"Chahat\",\n        \"email\": \"chahat@xambit.io\",\n        \"perm\": 2\n    }\n}"
						}
					]
				},
				{
					"name": "Request basic analysis for a GSTIN",
					"request": {
						"method": "POST",
						"header": [
							{
								"key": "X-HOST",
								"value": "{{xambit_api_host}}",
								"type": "text"
							},
							{
								"key": "X-KEY",
								"value": "{{xambit_api_key}}",
								"type": "text"
							},
							{
								"key": "Content-Type",
								"value": "application/json",
								"type": "text"
							}
						],
						"body": {
							"mode": "raw",
							"raw": "{\n    \"fin_years\": 1,\n    \"aggregate\": true,\n    \"infer\": false,\n    \"hook\": {\n        \"url\": \"example.com/endpoint\",\n        \"headers\": {\n            \"test_key\": \"test_value\"\n        },\n        \"method\": \"POST\"\n    }\n}"
						},
						"url": {
							"raw": "https://xapp-gstr-5qxdkkqowq-el.a.run.app/api/{{xambit_gst_xapp_id}}/gstin/{{gstin_number}}/basic",
							"protocol": "https",
							"host": [
								"xapp-gstr-5qxdkkqowq-el",
								"a",
								"run",
								"app"
							],
							"path": [
								"api",
								"{{xambit_gst_xapp_id}}",
								"gstin",
								"{{gstin_number}}",
								"basic"
							]
						},
						"description": "This is the main endpoint!  \n  \nThis requests creates a new GSTIN basic analysis request. The basic part means that information primarily from GSTR3B will be used to derive the metrics.\n\nThis request can be initiated only after you have created the GSTIN in the system and then completed auth flow via OTP. The parameters to be sent are"
					},
					"response": [
						{
							"name": "Check if GSTIN analysis exists",
							"originalRequest": {
								"method": "GET",
								"header": [
									{
										"key": "X-HOST",
										"value": "{{xambit_api_host}}",
										"type": "text"
									},
									{
										"key": "X-KEY",
										"value": "{{xambit_api_key}}",
										"type": "text"
									},
									{
										"key": "Content-Type",
										"value": "application/json",
										"type": "text"
									}
								],
								"url": {
									"raw": "https://xapp-gstr-5qxdkkqowq-el.a.run.app/api/{{xambit_gst_xapp_id}}/gstin/{{gstin_number}}",
									"protocol": "https",
									"host": [
										"xapp-gstr-5qxdkkqowq-el",
										"a",
										"run",
										"app"
									],
									"path": [
										"api",
										"{{xambit_gst_xapp_id}}",
										"gstin",
										"{{gstin_number}}"
									]
								}
							},
							"status": "OK",
							"code": 200,
							"_postman_previewlanguage": "json",
							"header": [
								{
									"key": "content-type",
									"value": "application/json"
								},
								{
									"key": "Content-Length",
									"value": "1091"
								},
								{
									"key": "date",
									"value": "Fri, 17 Nov 2023 06:06:36 GMT"
								},
								{
									"key": "server",
									"value": "Google Frontend"
								},
								{
									"key": "traceparent",
									"value": "00-1678074014e92c6436b0fb04e2d91371-ca8df44bfb88b0ae-01"
								},
								{
									"key": "x-cloud-trace-context",
									"value": "1678074014e92c6436b0fb04e2d91371/14595590574557409454;o=1"
								},
								{
									"key": "Alt-Svc",
									"value": "h3=\":443\"; ma=2592000,h3-29=\":443\"; ma=2592000"
								}
							],
							"cookie": [],
							"body": "{\n    \"id\": \"g-col-01HF64AXQD9HRDETCAA1SH4SN9\",\n    \"gstin\": \"29AAPCM6632E1Z5\",\n    \"status\": 0,\n    \"business\": {\n        \"name\": \"MYTHIKSHA SCHOOL PRIVATE LIMITED\",\n        \"ids\": [\n            {\n                \"id_kind\": 1,\n                \"id\": \"29AAPCM6632E1Z5\"\n            },\n            {\n                \"id_kind\": 2,\n                \"id\": \"AAPCM6632E\"\n            }\n        ],\n        \"promoters\": [],\n        \"trade_name\": null,\n        \"alt_name\": null,\n        \"address\": {\n            \"line1\": \"L-148, HSR LAYOUT\",\n            \"line2\": \"5th Main Road\",\n            \"city\": \"Bengaluru\",\n            \"state_code\": null,\n            \"state\": \"Karnataka\",\n            \"postal_code\": \"560102\",\n            \"country\": \"IN\"\n        },\n        \"other_ids\": [],\n        \"email\": null,\n        \"phone\": null,\n        \"bank\": null,\n        \"cheque\": null,\n        \"wire\": null,\n        \"website\": null\n    },\n    \"gstrbusiness\": {\n        \"kind\": \"Private Limited Company\",\n        \"jurisdiction_name\": \"RANGE-CSD5\",\n        \"jurisdiction_code\": \"YV0503\",\n        \"taxpayer_kind\": \"Regular\",\n        \"einvoice_status\": false,\n        \"nature_of_business\": [\n            \"Supplier of Services\"\n        ],\n        \"date_of_registration\": \"2022-07-07\",\n        \"jurisdiction_state_name\": \"LGSTO 17- Bengaluru\",\n        \"jurisdiction_state_code\": \"KA130\",\n        \"date_cancel\": null\n    },\n    \"entries\": [],\n    \"metrics\": [],\n    \"created\": \"2023-11-14 05:19:46.546542\",\n    \"updated\": \"2023-11-14 05:19:46.546542\",\n    \"period\": null,\n    \"authdate\": null,\n    \"creator\": {\n        \"id\": \"u-01H7CDJW728ZCAA0C7XYNNXFVT\",\n        \"name\": \"Chahat\",\n        \"email\": \"chahat@xambit.io\",\n        \"perm\": 2\n    }\n}"
						}
					]
				}
			]
		},
		{
			"name": "Bank Statement Analyser",
			"item": [
				{
					"name": "Create new file collection and analyse file as multi part form",
					"request": {
						"method": "PUT",
						"header": [
							{
								"key": "X-HOST",
								"value": "{{xambit_api_host}}",
								"type": "text"
							},
							{
								"key": "X-KEY",
								"value": "{{xambit_api_key}}",
								"type": "text"
							}
						],
						"body": {
							"mode": "formdata",
							"formdata": [
								{
									"key": "aggregate",
									"value": "true",
									"description": "Whether to run aggregation to calculate metrics (should set to true)",
									"type": "text"
								},
								{
									"key": "infer",
									"value": "true",
									"description": "Whether to use xAmbit AI to generate summary report",
									"type": "text",
									"disabled": true
								},
								{
									"key": "hookurl",
									"value": "https://05b3-2402-e280-3e09-3c8-f410-ea03-6feb-8731.ngrok-free.app",
									"description": "URL to which xAmbit should send reponse",
									"type": "text"
								},
								{
									"key": "file",
									"type": "file",
									"src": "/Users/harshad/Desktop/test_png_statement.png"
								},
								{
									"key": "hookauth",
									"value": "{\"test_key\": \"test_value\"}",
									"description": "Some parameters like credentials for webhook URL where xAmbit will post the results",
									"type": "text"
								}
							]
						},
						"url": {
							"raw": "{{xambit_bankstat_url}}/api/{{xambit_bankstat_xapp_id}}/collection",
							"host": [
								"{{xambit_bankstat_url}}"
							],
							"path": [
								"api",
								"{{xambit_bankstat_xapp_id}}",
								"collection"
							]
						},
						"description": "Create a file collection for bank statement analysis by adding one single file for analysis. This request returns 200 OK if everything is found in order.\n\nThe parameters in the header are documented below. Note that this API works on **WebHook Post** basis for response. You do not get bank statement analysis result in response immediately. The result will be posted to the hookurl you have specified in the data!\n\n- Aggregate: bool, if set to true, xAmbit extracts metrics like check bounce count, EMI bounce count etc. Can be set to false if you need only the raw transaction level data from the statement.\n    \n- Infer: bool, if set to true, xAmbit AI will try to generate a text summary of all the transactional data and its metrics.\n    \n- hookurl: where to post results of the analysis aka webhook URL\n    \n- hookauth: if your webhook URL needs some authentication to enable us to post result, set them here as a hashmap key-value pairs.\n    \n- file: multipart form data which contains actual content of the file to be analysed."
					},
					"response": []
				},
				{
					"name": "Create new file collection and analyse with json data",
					"request": {
						"method": "POST",
						"header": [
							{
								"key": "X-HOST",
								"value": "{{xambit_api_host}}",
								"type": "text"
							},
							{
								"key": "X-KEY",
								"value": "{{xambit_api_key}}",
								"type": "text"
							}
						],
						"body": {
							"mode": "raw",
							"raw": "{\n    \"file\": {\n        \"blob\": \"<file data read as byte array Array[Uint8]>\",\n        \"category\": 5,\n        \"name\": \"some_name_for_file.pdf\"\n    },\n    \"aggregate\": true,\n    \"infer\": true,\n    \"hook\": {\n        \"url\": \"example.com\",\n        \"method\": \"POST\",\n        \"headers\": {\n            \"test_key\": \"test_value\"\n        }\n    }\n}",
							"options": {
								"raw": {
									"language": "json"
								}
							}
						},
						"url": {
							"raw": "{{xambit_bankstat_url}}/api/{{xambit_bankstat_xapp_id}}/collection",
							"host": [
								"{{xambit_bankstat_url}}"
							],
							"path": [
								"api",
								"{{xambit_bankstat_xapp_id}}",
								"collection"
							]
						},
						"description": "Create a file collection for bank statement analysis by adding one single file for analysis. This request returns 200 OK if everything is found in order.\n\nThe parameters in the header are documented below. Note that this API works on **WebHook Post** basis for response. You do not get bank statement analysis result in response immediately. The result will be posted to the hookurl you have specified in the data!\n\n- Aggregate: bool, if set to true, xAmbit extracts metrics like check bounce count, EMI bounce count etc. Can be set to false if you need only the raw transaction level data from the statement.\n    \n- Infer: bool, if set to true, xAmbit AI will try to generate a text summary of all the transactional data and its metrics.\n    \n- hookurl: where to post results of the analysis aka webhook URL\n    \n- hookauth: if your webhook URL needs some authentication to enable us to post result, set them here as a hashmap key-value pairs.\n    \n- file: multipart form data which contains actual content of the file to be analysed."
					},
					"response": []
				},
				{
					"name": "Get data for already analysed collection",
					"request": {
						"method": "GET",
						"header": [
							{
								"key": "X-HOST",
								"value": "{{xambit_api_host}}",
								"type": "text"
							},
							{
								"key": "X-KEY",
								"value": "{{xambit_api_key}}",
								"type": "text"
							}
						],
						"url": {
							"raw": "{{xambit_bankstat_url}}/api/{{xambit_bankstat_xapp_id}}/collection/{{collection_id}}",
							"host": [
								"{{xambit_bankstat_url}}"
							],
							"path": [
								"api",
								"{{xambit_bankstat_xapp_id}}",
								"collection",
								"{{collection_id}}"
							]
						}
					},
					"response": []
				},
				{
					"name": "Delete already analysed collection",
					"request": {
						"method": "DELETE",
						"header": [
							{
								"key": "X-HOST",
								"value": "{{xambit_api_host}}",
								"type": "text"
							},
							{
								"key": "X-KEY",
								"value": "{{xambit_api_key}}",
								"type": "text"
							}
						],
						"url": {
							"raw": "{{xambit_bankstat_url}}/api/{{xambit_bankstat_xapp_id}}/collection/{{collection_id}}",
							"host": [
								"{{xambit_bankstat_url}}"
							],
							"path": [
								"api",
								"{{xambit_bankstat_xapp_id}}",
								"collection",
								"{{collection_id}}"
							]
						},
						"description": "THIS API IS NOT YET IMPLEMENTED. It is a work in progress!"
					},
					"response": []
				},
				{
					"name": "Add a file to existing collection as multi part form and analyse",
					"request": {
						"method": "PUT",
						"header": [
							{
								"key": "X-HOST",
								"value": "{{xambit_api_host}}",
								"type": "text"
							},
							{
								"key": "X-KEY",
								"value": "{{xambit_api_key}}",
								"type": "text"
							}
						],
						"body": {
							"mode": "formdata",
							"formdata": [
								{
									"key": "aggregate",
									"value": "true",
									"description": "Whether to run aggregation to calculate metrics (should set to true)",
									"type": "text"
								},
								{
									"key": "infer",
									"value": "true",
									"description": "Whether to use xAmbit AI to generate summary report",
									"type": "text"
								},
								{
									"key": "hookurl",
									"value": "example.com",
									"description": "URL to which xAmbit should send reponse",
									"type": "text"
								},
								{
									"key": "file",
									"type": "file",
									"src": "/Users/harshad/Desktop/hdfc_2_pages.pdf"
								},
								{
									"key": "hookauth",
									"value": "{\"test_key\": \"test_value\"}",
									"description": "Some parameters like credentials for webhook URL where xAmbit will post the results",
									"type": "text"
								}
							]
						},
						"url": {
							"raw": "{{xambit_bankstat_url}}/api/{{xambit_bankstat_xapp_id}}/collection/{{collection_id}}",
							"host": [
								"{{xambit_bankstat_url}}"
							],
							"path": [
								"api",
								"{{xambit_bankstat_xapp_id}}",
								"collection",
								"{{collection_id}}"
							]
						},
						"description": "Create a file collection for bank statement analysis by adding one single file for analysis. This request returns 200 OK if everything is found in order.\n\nThe parameters in the header are documented below. Note that this API works on **WebHook Post** basis for response. You do not get bank statement analysis result in response immediately. The result will be posted to the hookurl you have specified in the data!\n\n- Aggregate: bool, if set to true, xAmbit extracts metrics like check bounce count, EMI bounce count etc. Can be set to false if you need only the raw transaction level data from the statement.\n    \n- Infer: bool, if set to true, xAmbit AI will try to generate a text summary of all the transactional data and its metrics.\n    \n- hookurl: where to post results of the analysis aka webhook URL\n    \n- hookauth: if your webhook URL needs some authentication to enable us to post result, set them here as a hashmap key-value pairs.\n    \n- file: multipart form data which contains actual content of the file to be analysed."
					},
					"response": []
				},
				{
					"name": "Add a file to existing collection with json data and analyse",
					"request": {
						"method": "POST",
						"header": [
							{
								"key": "X-HOST",
								"value": "{{xambit_api_host}}",
								"type": "text"
							},
							{
								"key": "X-KEY",
								"value": "{{xambit_api_key}}",
								"type": "text"
							}
						],
						"body": {
							"mode": "raw",
							"raw": "{\n    \"file\": {\n        \"blob\": \"<file data read as byte array Array[Uint8]>\",\n        \"category\": 5,\n        \"name\": \"some_name_for_file.pdf\"\n    },\n    \"aggregate\": true,\n    \"infer\": true,\n    \"hook\": {\n        \"url\": \"example.com\",\n        \"method\": \"POST\",\n        \"headers\": {\n            \"test_key\": \"test_value\"\n        }\n    }\n}",
							"options": {
								"raw": {
									"language": "json"
								}
							}
						},
						"url": {
							"raw": "{{xambit_bankstat_url}}/api/{{xambit_bankstat_xapp_id}}/collection/{{collection_id}}",
							"host": [
								"{{xambit_bankstat_url}}"
							],
							"path": [
								"api",
								"{{xambit_bankstat_xapp_id}}",
								"collection",
								"{{collection_id}}"
							]
						},
						"description": "Create a file collection for bank statement analysis by adding one single file for analysis. This request returns 200 OK if everything is found in order.\n\nThe parameters in the header are documented below. Note that this API works on **WebHook Post** basis for response. You do not get bank statement analysis result in response immediately. The result will be posted to the hookurl you have specified in the data!\n\n- Aggregate: bool, if set to true, xAmbit extracts metrics like check bounce count, EMI bounce count etc. Can be set to false if you need only the raw transaction level data from the statement.\n    \n- Infer: bool, if set to true, xAmbit AI will try to generate a text summary of all the transactional data and its metrics.\n    \n- hookurl: where to post results of the analysis aka webhook URL\n    \n- hookauth: if your webhook URL needs some authentication to enable us to post result, set them here as a hashmap key-value pairs.\n    \n- file: multipart form data which contains actual content of the file to be analysed."
					},
					"response": []
				}
			],
			"description": "Detailed documentation can be found on xambit portal."
		}
	]
}